essentia/algorithms.py
essentia/pool.py
essentia/__init__.py
essentia/streaming.py
essentia/plotting.py
essentia/_essentia.cpython-310-i386-linux-gnu.so
essentia/translate.py
essentia/progress.py
essentia/common.py
essentia/utils.py
essentia/standard.py
essentia/essentia_extractor.py
essentia/extractor/beats.py
essentia/extractor/chords.py
essentia/extractor/segmentation_simple.py
essentia/extractor/squeezeInto.py
essentia/extractor/__init__.py
essentia/extractor/sfx.py
essentia/extractor/segmentation_bic.py
essentia/extractor/segmentation_max_energy.py
essentia/extractor/thumbnail.py
essentia/extractor/relativeioi.py
essentia/extractor/tonal.py
essentia/extractor/tempotap.py
essentia/extractor/scales.py
essentia/extractor/lowlevel.py
essentia/extractor/segmentation.py
essentia/extractor/panning.py
essentia/extractor/average_loudness.py
essentia/extractor/highlevel.py
essentia/extractor/onsetdetection.py
essentia/extractor/chords_dissonance_table.py
essentia/pytools/batch_extractors.py
essentia/pytools/spectral.py
essentia/pytools/__init__.py
essentia/pytools/io.py
essentia/pytools/extractors/__init__.py
essentia/pytools/extractors/melspectrogram.py
essentia/pytools/extractors/music_extractor.py
essentia/weka/__init__.py
essentia/weka/convert_essentia_to_weka.py
essentia/weka/arff2matlab.py
essentia/weka/wekafile.py
essentia-2.1b6.dev1034.dist-info/COPYING.txt
essentia-2.1b6.dev1034.dist-info/RECORD
essentia-2.1b6.dev1034.dist-info/METADATA
essentia-2.1b6.dev1034.dist-info/top_level.txt
essentia-2.1b6.dev1034.dist-info/WHEEL
essentia-2.1b6.dev1034.dist-info/AUTHORS
