Metadata-Version: 2.1
Name: essentia
Version: 2.1b6.dev1034
Summary: Library for audio and music analysis, description and synthesis
Home-page: http://essentia.upf.edu
Author: Dmitry Bogdanov
Author-email: dmitry.bogdanov@upf.edu
License: AGPLv3
Project-URL: Documentation, http://essentia.upf.edu
Project-URL: Source Code, https://github.com/MTG/essentia
Keywords: audio music sound dsp MIR
Platform: any
Classifier: License :: OSI Approved :: GNU Affero General Public License v3
Classifier: Development Status :: 4 - Beta
Classifier: Intended Audience :: Developers
Classifier: Intended Audience :: Science/Research
Classifier: Topic :: Software Development :: Libraries
Classifier: Topic :: Multimedia :: Sound/Audio :: Analysis
Classifier: Topic :: Multimedia :: Sound/Audio :: Sound Synthesis
Classifier: Operating System :: POSIX
Classifier: Operating System :: MacOS :: MacOS X
Classifier: Programming Language :: C++
Classifier: Programming Language :: Python
Classifier: Programming Language :: Python :: 2
Classifier: Programming Language :: Python :: 3
License-File: COPYING.txt
License-File: AUTHORS
Requires-Dist: numpy (>=1.8.2)
Requires-Dist: six
Requires-Dist: pyyaml
